{"Season":"2023-24","Lg":"NBA","Tm":"1st","Voting":"(V)","Unnamed: 4":"Nikola Joki\u0107 C","Unnamed: 5":"Giannis Antetokounmpo F","Unnamed: 6":"Jayson Tatum F","Unnamed: 7":"Luka Don\u010di\u0107 G","Unnamed: 8":"Shai Gilgeous-Alexander G"}
{"Season":"2023-24","Lg":"NBA","Tm":"2nd","Voting":"(V)","Unnamed: 4":"Anthony Davis C","Unnamed: 5":"Kevin Durant F","Unnamed: 6":"Kawhi Leonard F","Unnamed: 7":"Jalen Brunson G","Unnamed: 8":"Anthony Edwards G"}
{"Season":"2023-24","Lg":"NBA","Tm":"3rd","Voting":"(V)","Unnamed: 4":"LeBron James F","Unnamed: 5":"Domantas Sabonis F","Unnamed: 6":"Devin Booker G","Unnamed: 7":"Stephen Curry G","Unnamed: 8":"Tyrese Haliburton G"}
{"Season":"2022-23","Lg":"NBA","Tm":"1st","Voting":"(V)","Unnamed: 4":"Joel Embiid C","Unnamed: 5":"Giannis Antetokounmpo F","Unnamed: 6":"Jayson Tatum F","Unnamed: 7":"Luka Don\u010di\u0107 G","Unnamed: 8":"Shai Gilgeous-Alexander G"}
{"Season":"2022-23","Lg":"NBA","Tm":"2nd","Voting":"(V)","Unnamed: 4":"Nikola Joki\u0107 C","Unnamed: 5":"Jimmy Butler F","Unnamed: 6":"Jaylen Brown F","Unnamed: 7":"Donovan Mitchell G","Unnamed: 8":"Stephen Curry G"}
{"Season":"2022-23","Lg":"NBA","Tm":"3rd","Voting":"(V)","Unnamed: 4":"Domantas Sabonis C","Unnamed: 5":"LeBron James F","Unnamed: 6":"Julius Randle F","Unnamed: 7":"De'Aaron Fox G","Unnamed: 8":"Damian Lillard G"}
{"Season":"2021-22","Lg":"NBA","Tm":"1st","Voting":"(V)","Unnamed: 4":"Nikola Joki\u0107 C","Unnamed: 5":"Giannis Antetokounmpo F","Unnamed: 6":"Jayson Tatum F","Unnamed: 7":"Luka Don\u010di\u0107 G","Unnamed: 8":"Devin Booker G"}
{"Season":"2021-22","Lg":"NBA","Tm":"2nd","Voting":"(V)","Unnamed: 4":"Joel Embiid C","Unnamed: 5":"Kevin Durant F","Unnamed: 6":"DeMar DeRozan F","Unnamed: 7":"Ja Morant G","Unnamed: 8":"Stephen Curry G"}
{"Season":"2021-22","Lg":"NBA","Tm":"3rd","Voting":"(V)","Unnamed: 4":"Karl-Anthony Towns C","Unnamed: 5":"LeBron James F","Unnamed: 6":"Pascal Siakam F","Unnamed: 7":"Chris Paul G","Unnamed: 8":"Trae Young G"}
{"Season":"2020-21","Lg":"NBA","Tm":"1st","Voting":"(V)","Unnamed: 4":"Nikola Joki\u0107 C","Unnamed: 5":"Giannis Antetokounmpo F","Unnamed: 6":"Kawhi Leonard F","Unnamed: 7":"Stephen Curry G","Unnamed: 8":"Luka Don\u010di\u0107 G"}
{"Season":"2020-21","Lg":"NBA","Tm":"2nd","Voting":"(V)","Unnamed: 4":"Joel Embiid C","Unnamed: 5":"Julius Randle F","Unnamed: 6":"LeBron James F","Unnamed: 7":"Chris Paul G","Unnamed: 8":"Damian Lillard G"}
{"Season":"2020-21","Lg":"NBA","Tm":"3rd","Voting":"(V)","Unnamed: 4":"Rudy Gobert C","Unnamed: 5":"Jimmy Butler F","Unnamed: 6":"Paul George F","Unnamed: 7":"Bradley Beal G","Unnamed: 8":"Kyrie Irving G"}
{"Season":"2019-20","Lg":"NBA","Tm":"1st","Voting":"(V)","Unnamed: 4":"Anthony Davis C","Unnamed: 5":"Giannis Antetokounmpo F","Unnamed: 6":"LeBron James F","Unnamed: 7":"James Harden G","Unnamed: 8":"Luka Don\u010di\u0107 G"}
{"Season":"2019-20","Lg":"NBA","Tm":"2nd","Voting":"(V)","Unnamed: 4":"Nikola Joki\u0107 C","Unnamed: 5":"Kawhi Leonard F","Unnamed: 6":"Pascal Siakam F","Unnamed: 7":"Damian Lillard G","Unnamed: 8":"Chris Paul G"}
{"Season":"2019-20","Lg":"NBA","Tm":"3rd","Voting":"(V)","Unnamed: 4":"Rudy Gobert C","Unnamed: 5":"Jayson Tatum F","Unnamed: 6":"Jimmy Butler F","Unnamed: 7":"Ben Simmons G","Unnamed: 8":"Russell Westbrook G"}
{"Season":"2018-19","Lg":"NBA","Tm":"1st","Voting":"(V)","Unnamed: 4":"Nikola Joki\u0107 C","Unnamed: 5":"Giannis Antetokounmpo F","Unnamed: 6":"Paul George F","Unnamed: 7":"James Harden G","Unnamed: 8":"Stephen Curry G"}
{"Season":"2018-19","Lg":"NBA","Tm":"2nd","Voting":"(V)","Unnamed: 4":"Joel Embiid C","Unnamed: 5":"Kevin Durant F","Unnamed: 6":"Kawhi Leonard F","Unnamed: 7":"Damian Lillard G","Unnamed: 8":"Kyrie Irving G"}
{"Season":"2018-19","Lg":"NBA","Tm":"3rd","Voting":"(V)","Unnamed: 4":"Rudy Gobert C","Unnamed: 5":"LeBron James F","Unnamed: 6":"Blake Griffin F","Unnamed: 7":"Kemba Walker G","Unnamed: 8":"Russell Westbrook G"}
{"Season":"2017-18","Lg":"NBA","Tm":"1st","Voting":"(V)","Unnamed: 4":"Anthony Davis C","Unnamed: 5":"LeBron James F","Unnamed: 6":"Kevin Durant F","Unnamed: 7":"Damian Lillard G","Unnamed: 8":"James Harden G"}
{"Season":"2017-18","Lg":"NBA","Tm":"2nd","Voting":"(V)","Unnamed: 4":"Joel Embiid C","Unnamed: 5":"Giannis Antetokounmpo F","Unnamed: 6":"LaMarcus Aldridge F","Unnamed: 7":"Russell Westbrook G","Unnamed: 8":"DeMar DeRozan G"}
{"Season":"2017-18","Lg":"NBA","Tm":"3rd","Voting":"(V)","Unnamed: 4":"Karl-Anthony Towns C","Unnamed: 5":"Jimmy Butler F","Unnamed: 6":"Paul George F","Unnamed: 7":"Stephen Curry G","Unnamed: 8":"Victor Oladipo G"}
{"Season":"2016-17","Lg":"NBA","Tm":"1st","Voting":"(V)","Unnamed: 4":"Anthony Davis C","Unnamed: 5":"LeBron James F","Unnamed: 6":"Kawhi Leonard F","Unnamed: 7":"James Harden G","Unnamed: 8":"Russell Westbrook G"}
{"Season":"2016-17","Lg":"NBA","Tm":"2nd","Voting":"(V)","Unnamed: 4":"Rudy Gobert C","Unnamed: 5":"Giannis Antetokounmpo F","Unnamed: 6":"Kevin Durant F","Unnamed: 7":"Stephen Curry G","Unnamed: 8":"Isaiah Thomas G"}
{"Season":"2016-17","Lg":"NBA","Tm":"3rd","Voting":"(V)","Unnamed: 4":"DeAndre Jordan C","Unnamed: 5":"Draymond Green F","Unnamed: 6":"Jimmy Butler F","Unnamed: 7":"John Wall G","Unnamed: 8":"DeMar DeRozan G"}
{"Season":"2015-16","Lg":"NBA","Tm":"1st","Voting":"(V)","Unnamed: 4":"DeAndre Jordan C","Unnamed: 5":"LeBron James F","Unnamed: 6":"Kawhi Leonard F","Unnamed: 7":"Stephen Curry G","Unnamed: 8":"Russell Westbrook G"}
{"Season":"2015-16","Lg":"NBA","Tm":"2nd","Voting":"(V)","Unnamed: 4":"DeMarcus Cousins C","Unnamed: 5":"Kevin Durant F","Unnamed: 6":"Draymond Green F","Unnamed: 7":"Chris Paul G","Unnamed: 8":"Damian Lillard G"}
{"Season":"2015-16","Lg":"NBA","Tm":"3rd","Voting":"(V)","Unnamed: 4":"Andre Drummond C","Unnamed: 5":"Paul George F","Unnamed: 6":"LaMarcus Aldridge F","Unnamed: 7":"Klay Thompson G","Unnamed: 8":"Kyle Lowry G"}
{"Season":"2014-15","Lg":"NBA","Tm":"1st","Voting":"(V)","Unnamed: 4":"Marc Gasol C","Unnamed: 5":"LeBron James F","Unnamed: 6":"Anthony Davis F","Unnamed: 7":"Stephen Curry G","Unnamed: 8":"James Harden G"}
{"Season":"2014-15","Lg":"NBA","Tm":"2nd","Voting":"(V)","Unnamed: 4":"DeMarcus Cousins C","Unnamed: 5":"Pau Gasol C","Unnamed: 6":"LaMarcus Aldridge F","Unnamed: 7":"Russell Westbrook G","Unnamed: 8":"Chris Paul G"}
{"Season":"2014-15","Lg":"NBA","Tm":"3rd","Voting":"(V)","Unnamed: 4":"DeAndre Jordan C","Unnamed: 5":"Blake Griffin F","Unnamed: 6":"Tim Duncan F","Unnamed: 7":"Klay Thompson G","Unnamed: 8":"Kyrie Irving G"}
{"Season":"2013-14","Lg":"NBA","Tm":"1st","Voting":"(V)","Unnamed: 4":"Joakim Noah C","Unnamed: 5":"Kevin Durant F","Unnamed: 6":"LeBron James F","Unnamed: 7":"James Harden G","Unnamed: 8":"Chris Paul G"}
{"Season":"2013-14","Lg":"NBA","Tm":"2nd","Voting":"(V)","Unnamed: 4":"Dwight Howard C","Unnamed: 5":"Blake Griffin F","Unnamed: 6":"Kevin Love F","Unnamed: 7":"Stephen Curry G","Unnamed: 8":"Tony Parker G"}
{"Season":"2013-14","Lg":"NBA","Tm":"3rd","Voting":"(V)","Unnamed: 4":"Al Jefferson C","Unnamed: 5":"Paul George F","Unnamed: 6":"LaMarcus Aldridge F","Unnamed: 7":"Goran Dragi\u0107 G","Unnamed: 8":"Damian Lillard G"}
{"Season":"2012-13","Lg":"NBA","Tm":"1st","Voting":"(V)","Unnamed: 4":"Tim Duncan C","Unnamed: 5":"Kevin Durant F","Unnamed: 6":"LeBron James F","Unnamed: 7":"Kobe Bryant G","Unnamed: 8":"Chris Paul G"}
{"Season":"2012-13","Lg":"NBA","Tm":"2nd","Voting":"(V)","Unnamed: 4":"Marc Gasol C","Unnamed: 5":"Carmelo Anthony F","Unnamed: 6":"Blake Griffin F","Unnamed: 7":"Tony Parker G","Unnamed: 8":"Russell Westbrook G"}
{"Season":"2012-13","Lg":"NBA","Tm":"3rd","Voting":"(V)","Unnamed: 4":"Dwight Howard C","Unnamed: 5":"Paul George F","Unnamed: 6":"David Lee F","Unnamed: 7":"James Harden G","Unnamed: 8":"Dwyane Wade G"}
{"Season":"2011-12","Lg":"NBA","Tm":"1st","Voting":"(V)","Unnamed: 4":"Dwight Howard C","Unnamed: 5":"Kevin Durant F","Unnamed: 6":"LeBron James F","Unnamed: 7":"Kobe Bryant G","Unnamed: 8":"Chris Paul G"}
{"Season":"2011-12","Lg":"NBA","Tm":"2nd","Voting":"(V)","Unnamed: 4":"Andrew Bynum C","Unnamed: 5":"Blake Griffin F","Unnamed: 6":"Kevin Love F","Unnamed: 7":"Tony Parker G","Unnamed: 8":"Russell Westbrook G"}
{"Season":"2011-12","Lg":"NBA","Tm":"3rd","Voting":"(V)","Unnamed: 4":"Tyson Chandler C","Unnamed: 5":"Carmelo Anthony F","Unnamed: 6":"Dirk Nowitzki F","Unnamed: 7":"Rajon Rondo G","Unnamed: 8":"Dwyane Wade G"}
{"Season":"2010-11","Lg":"NBA","Tm":"1st","Voting":"(V)","Unnamed: 4":"Dwight Howard C","Unnamed: 5":"Kevin Durant F","Unnamed: 6":"LeBron James F","Unnamed: 7":"Kobe Bryant G","Unnamed: 8":"Derrick Rose G"}
{"Season":"2010-11","Lg":"NBA","Tm":"2nd","Voting":"(V)","Unnamed: 4":"Amar'e Stoudemire C","Unnamed: 5":"Pau Gasol F","Unnamed: 6":"Dirk Nowitzki F","Unnamed: 7":"Dwyane Wade G","Unnamed: 8":"Russell Westbrook G"}
{"Season":"2010-11","Lg":"NBA","Tm":"3rd","Voting":"(V)","Unnamed: 4":"Al Horford C","Unnamed: 5":"LaMarcus Aldridge F","Unnamed: 6":"Zach Randolph F","Unnamed: 7":"Manu Gin\u00f3bili G","Unnamed: 8":"Chris Paul G"}
{"Season":"2009-10","Lg":"NBA","Tm":"1st","Voting":"(V)","Unnamed: 4":"Dwight Howard C","Unnamed: 5":"Kevin Durant F","Unnamed: 6":"LeBron James F","Unnamed: 7":"Kobe Bryant G","Unnamed: 8":"Dwyane Wade G"}
{"Season":"2009-10","Lg":"NBA","Tm":"2nd","Voting":"(V)","Unnamed: 4":"Amar'e Stoudemire C","Unnamed: 5":"Carmelo Anthony F","Unnamed: 6":"Dirk Nowitzki F","Unnamed: 7":"Steve Nash G","Unnamed: 8":"Deron Williams G"}
{"Season":"2009-10","Lg":"NBA","Tm":"3rd","Voting":"(V)","Unnamed: 4":"Andrew Bogut C","Unnamed: 5":"Tim Duncan F","Unnamed: 6":"Pau Gasol F","Unnamed: 7":"Joe Johnson G","Unnamed: 8":"Brandon Roy G"}
{"Season":"2008-09","Lg":"NBA","Tm":"1st","Voting":"(V)","Unnamed: 4":"Dwight Howard C","Unnamed: 5":"LeBron James F","Unnamed: 6":"Dirk Nowitzki F","Unnamed: 7":"Kobe Bryant G","Unnamed: 8":"Dwyane Wade G"}
{"Season":"2008-09","Lg":"NBA","Tm":"2nd","Voting":"(V)","Unnamed: 4":"Yao Ming C","Unnamed: 5":"Tim Duncan F","Unnamed: 6":"Paul Pierce F","Unnamed: 7":"Chris Paul G","Unnamed: 8":"Brandon Roy G"}
{"Season":"2008-09","Lg":"NBA","Tm":"3rd","Voting":"(V)","Unnamed: 4":"Shaquille O'Neal C","Unnamed: 5":"Carmelo Anthony F","Unnamed: 6":"Pau Gasol F","Unnamed: 7":"Chauncey Billups G","Unnamed: 8":"Tony Parker G"}
{"Season":"2007-08","Lg":"NBA","Tm":"1st","Voting":"(V)","Unnamed: 4":"Dwight Howard C","Unnamed: 5":"Kevin Garnett F","Unnamed: 6":"LeBron James F","Unnamed: 7":"Kobe Bryant G","Unnamed: 8":"Chris Paul G"}
{"Season":"2007-08","Lg":"NBA","Tm":"2nd","Voting":"(V)","Unnamed: 4":"Amar'e Stoudemire C","Unnamed: 5":"Tim Duncan F","Unnamed: 6":"Dirk Nowitzki F","Unnamed: 7":"Steve Nash G","Unnamed: 8":"Deron Williams G"}
{"Season":"2007-08","Lg":"NBA","Tm":"3rd","Voting":"(V)","Unnamed: 4":"Yao Ming C","Unnamed: 5":"Carlos Boozer F","Unnamed: 6":"Paul Pierce F","Unnamed: 7":"Manu Gin\u00f3bili G","Unnamed: 8":"Tracy McGrady G"}
{"Season":"2006-07","Lg":"NBA","Tm":"1st","Voting":"(V)","Unnamed: 4":"Amar'e Stoudemire C","Unnamed: 5":"Tim Duncan F","Unnamed: 6":"Dirk Nowitzki F","Unnamed: 7":"Kobe Bryant G","Unnamed: 8":"Steve Nash G"}
{"Season":"2006-07","Lg":"NBA","Tm":"2nd","Voting":"(V)","Unnamed: 4":"Yao Ming C","Unnamed: 5":"Chris Bosh F","Unnamed: 6":"LeBron James F","Unnamed: 7":"Gilbert Arenas G","Unnamed: 8":"Tracy McGrady G"}
{"Season":"2006-07","Lg":"NBA","Tm":"3rd","Voting":"(V)","Unnamed: 4":"Dwight Howard C","Unnamed: 5":"Carmelo Anthony F","Unnamed: 6":"Kevin Garnett F","Unnamed: 7":"Chauncey Billups G","Unnamed: 8":"Dwyane Wade G"}
{"Season":"2005-06","Lg":"NBA","Tm":"1st","Voting":"(V)","Unnamed: 4":"Shaquille O'Neal C","Unnamed: 5":"LeBron James F","Unnamed: 6":"Dirk Nowitzki F","Unnamed: 7":"Kobe Bryant G","Unnamed: 8":"Steve Nash G"}
{"Season":"2005-06","Lg":"NBA","Tm":"2nd","Voting":"(V)","Unnamed: 4":"Ben Wallace C","Unnamed: 5":"Elton Brand F","Unnamed: 6":"Tim Duncan F","Unnamed: 7":"Chauncey Billups G","Unnamed: 8":"Dwyane Wade G"}
{"Season":"2005-06","Lg":"NBA","Tm":"3rd","Voting":"(V)","Unnamed: 4":"Yao Ming C","Unnamed: 5":"Carmelo Anthony F","Unnamed: 6":"Shawn Marion F","Unnamed: 7":"Gilbert Arenas G","Unnamed: 8":"Allen Iverson G"}
{"Season":"2004-05","Lg":"NBA","Tm":"1st","Voting":"(V)","Unnamed: 4":"Shaquille O'Neal C","Unnamed: 5":"Tim Duncan F","Unnamed: 6":"Dirk Nowitzki F","Unnamed: 7":"Allen Iverson G","Unnamed: 8":"Steve Nash G"}
{"Season":"2004-05","Lg":"NBA","Tm":"2nd","Voting":"(V)","Unnamed: 4":"Amar'e Stoudemire C","Unnamed: 5":"Kevin Garnett F","Unnamed: 6":"LeBron James F","Unnamed: 7":"Ray Allen G","Unnamed: 8":"Dwyane Wade G"}
{"Season":"2004-05","Lg":"NBA","Tm":"3rd","Voting":"(V)","Unnamed: 4":"Ben Wallace C","Unnamed: 5":"Shawn Marion F","Unnamed: 6":"Tracy McGrady F","Unnamed: 7":"Gilbert Arenas G","Unnamed: 8":"Kobe Bryant G"}
{"Season":"2003-04","Lg":"NBA","Tm":"1st","Voting":"(V)","Unnamed: 4":"Shaquille O'Neal C","Unnamed: 5":"Tim Duncan F","Unnamed: 6":"Kevin Garnett F","Unnamed: 7":"Kobe Bryant G","Unnamed: 8":"Jason Kidd G"}
{"Season":"2003-04","Lg":"NBA","Tm":"2nd","Voting":"(V)","Unnamed: 4":"Ben Wallace C","Unnamed: 5":"Jermaine O'Neal F","Unnamed: 6":"Peja Stojakovi\u0107 F","Unnamed: 7":"Sam Cassell G","Unnamed: 8":"Tracy McGrady G"}
{"Season":"2003-04","Lg":"NBA","Tm":"3rd","Voting":"(V)","Unnamed: 4":"Yao Ming C","Unnamed: 5":"Metta World Peace F","Unnamed: 6":"Dirk Nowitzki F","Unnamed: 7":"Baron Davis G","Unnamed: 8":"Michael Redd G"}
{"Season":"2002-03","Lg":"NBA","Tm":"1st","Voting":"(V)","Unnamed: 4":"Shaquille O'Neal C","Unnamed: 5":"Tim Duncan F","Unnamed: 6":"Kevin Garnett F","Unnamed: 7":"Kobe Bryant G","Unnamed: 8":"Tracy McGrady G"}
{"Season":"2002-03","Lg":"NBA","Tm":"2nd","Voting":"(V)","Unnamed: 4":"Ben Wallace C","Unnamed: 5":"Dirk Nowitzki F","Unnamed: 6":"Chris Webber F","Unnamed: 7":"Allen Iverson G","Unnamed: 8":"Jason Kidd G"}
{"Season":"2002-03","Lg":"NBA","Tm":"3rd","Voting":"(V)","Unnamed: 4":"Jermaine O'Neal C","Unnamed: 5":"Jamal Mashburn F","Unnamed: 6":"Paul Pierce F","Unnamed: 7":"Stephon Marbury G","Unnamed: 8":"Steve Nash G"}
{"Season":"2001-02","Lg":"NBA","Tm":"1st","Voting":"(V)","Unnamed: 4":"Shaquille O'Neal C","Unnamed: 5":"Tim Duncan F","Unnamed: 6":"Tracy McGrady F","Unnamed: 7":"Kobe Bryant G","Unnamed: 8":"Jason Kidd G"}
{"Season":"2001-02","Lg":"NBA","Tm":"2nd","Voting":"(V)","Unnamed: 4":"Dirk Nowitzki C","Unnamed: 5":"Kevin Garnett F","Unnamed: 6":"Chris Webber F","Unnamed: 7":"Allen Iverson G","Unnamed: 8":"Gary Payton G"}
{"Season":"2001-02","Lg":"NBA","Tm":"3rd","Voting":"(V)","Unnamed: 4":"Dikembe Mutombo C","Unnamed: 5":"Jermaine O'Neal F","Unnamed: 6":"Ben Wallace F","Unnamed: 7":"Steve Nash G","Unnamed: 8":"Paul Pierce G"}
{"Season":"2000-01","Lg":"NBA","Tm":"1st","Voting":"(V)","Unnamed: 4":"Shaquille O'Neal C","Unnamed: 5":"Tim Duncan F","Unnamed: 6":"Chris Webber F","Unnamed: 7":"Allen Iverson G","Unnamed: 8":"Jason Kidd G"}
{"Season":"2000-01","Lg":"NBA","Tm":"2nd","Voting":"(V)","Unnamed: 4":"Dikembe Mutombo C","Unnamed: 5":"Vince Carter F","Unnamed: 6":"Kevin Garnett F","Unnamed: 7":"Kobe Bryant G","Unnamed: 8":"Tracy McGrady G"}
{"Season":"2000-01","Lg":"NBA","Tm":"3rd","Voting":"(V)","Unnamed: 4":"David Robinson C","Unnamed: 5":"Karl Malone F","Unnamed: 6":"Dirk Nowitzki F","Unnamed: 7":"Ray Allen G","Unnamed: 8":"Gary Payton G"}
{"Season":"1999-00","Lg":"NBA","Tm":"1st","Voting":"(V)","Unnamed: 4":"Shaquille O'Neal C","Unnamed: 5":"Tim Duncan F","Unnamed: 6":"Kevin Garnett F","Unnamed: 7":"Jason Kidd G","Unnamed: 8":"Gary Payton G"}
{"Season":"1999-00","Lg":"NBA","Tm":"2nd","Voting":"(V)","Unnamed: 4":"Alonzo Mourning C","Unnamed: 5":"Grant Hill F","Unnamed: 6":"Karl Malone F","Unnamed: 7":"Kobe Bryant G","Unnamed: 8":"Allen Iverson G"}
{"Season":"1999-00","Lg":"NBA","Tm":"3rd","Voting":"(V)","Unnamed: 4":"David Robinson C","Unnamed: 5":"Vince Carter F","Unnamed: 6":"Chris Webber F","Unnamed: 7":"Eddie Jones G","Unnamed: 8":"Stephon Marbury G"}
{"Season":"1998-99","Lg":"NBA","Tm":"1st","Voting":"(V)","Unnamed: 4":"Alonzo Mourning C","Unnamed: 5":"Tim Duncan F","Unnamed: 6":"Karl Malone F","Unnamed: 7":"Allen Iverson G","Unnamed: 8":"Jason Kidd G"}
{"Season":"1998-99","Lg":"NBA","Tm":"2nd","Voting":"(V)","Unnamed: 4":"Shaquille O'Neal C","Unnamed: 5":"Grant Hill F","Unnamed: 6":"Chris Webber F","Unnamed: 7":"Tim Hardaway G","Unnamed: 8":"Gary Payton G"}
{"Season":"1998-99","Lg":"NBA","Tm":"3rd","Voting":"(V)","Unnamed: 4":"Hakeem Olajuwon C","Unnamed: 5":"Kevin Garnett F","Unnamed: 6":"Antonio McDyess F","Unnamed: 7":"Kobe Bryant G","Unnamed: 8":"John Stockton G"}
{"Season":"1997-98","Lg":"NBA","Tm":"1st","Voting":"(V)","Unnamed: 4":"Shaquille O'Neal C","Unnamed: 5":"Tim Duncan F","Unnamed: 6":"Karl Malone F","Unnamed: 7":"Michael Jordan G","Unnamed: 8":"Gary Payton G"}
{"Season":"1997-98","Lg":"NBA","Tm":"2nd","Voting":"(V)","Unnamed: 4":"David Robinson C","Unnamed: 5":"Vin Baker F","Unnamed: 6":"Grant Hill F","Unnamed: 7":"Tim Hardaway G","Unnamed: 8":"Rod Strickland G"}
{"Season":"1997-98","Lg":"NBA","Tm":"3rd","Voting":"(V)","Unnamed: 4":"Dikembe Mutombo C","Unnamed: 5":"Scottie Pippen F","Unnamed: 6":"Glen Rice F","Unnamed: 7":"Reggie Miller G","Unnamed: 8":"Mitch Richmond G"}
{"Season":"1996-97","Lg":"NBA","Tm":"1st","Voting":"(V)","Unnamed: 4":"Hakeem Olajuwon C","Unnamed: 5":"Grant Hill F","Unnamed: 6":"Karl Malone F","Unnamed: 7":"Tim Hardaway G","Unnamed: 8":"Michael Jordan G"}
{"Season":"1996-97","Lg":"NBA","Tm":"2nd","Voting":"(V)","Unnamed: 4":"Patrick Ewing C","Unnamed: 5":"Scottie Pippen F","Unnamed: 6":"Glen Rice F","Unnamed: 7":"Gary Payton G","Unnamed: 8":"Mitch Richmond G"}
{"Season":"1996-97","Lg":"NBA","Tm":"3rd","Voting":"(V)","Unnamed: 4":"Shaquille O'Neal C","Unnamed: 5":"Vin Baker F","Unnamed: 6":"Anthony Mason F","Unnamed: 7":"Anfernee Hardaway G","Unnamed: 8":"John Stockton G"}
{"Season":"1995-96","Lg":"NBA","Tm":"1st","Voting":"(V)","Unnamed: 4":"David Robinson C","Unnamed: 5":"Karl Malone F","Unnamed: 6":"Scottie Pippen F","Unnamed: 7":"Anfernee Hardaway G","Unnamed: 8":"Michael Jordan G"}
{"Season":"1995-96","Lg":"NBA","Tm":"2nd","Voting":"(V)","Unnamed: 4":"Hakeem Olajuwon C","Unnamed: 5":"Grant Hill F","Unnamed: 6":"Shawn Kemp F","Unnamed: 7":"Gary Payton G","Unnamed: 8":"John Stockton G"}
{"Season":"1995-96","Lg":"NBA","Tm":"3rd","Voting":"(V)","Unnamed: 4":"Shaquille O'Neal C","Unnamed: 5":"Charles Barkley F","Unnamed: 6":"Juwan Howard F","Unnamed: 7":"Reggie Miller G","Unnamed: 8":"Mitch Richmond G"}
{"Season":"1994-95","Lg":"NBA","Tm":"1st","Voting":"(V)","Unnamed: 4":"David Robinson C","Unnamed: 5":"Karl Malone F","Unnamed: 6":"Scottie Pippen F","Unnamed: 7":"Anfernee Hardaway G","Unnamed: 8":"John Stockton G"}
{"Season":"1994-95","Lg":"NBA","Tm":"2nd","Voting":"(V)","Unnamed: 4":"Shaquille O'Neal C","Unnamed: 5":"Charles Barkley F","Unnamed: 6":"Shawn Kemp F","Unnamed: 7":"Gary Payton G","Unnamed: 8":"Mitch Richmond G"}
{"Season":"1994-95","Lg":"NBA","Tm":"3rd","Voting":"(V)","Unnamed: 4":"Hakeem Olajuwon C","Unnamed: 5":"Dennis Rodman F","Unnamed: 6":"Detlef Schrempf F","Unnamed: 7":"Clyde Drexler G","Unnamed: 8":"Reggie Miller G"}
{"Season":"1993-94","Lg":"NBA","Tm":"1st","Voting":"(V)","Unnamed: 4":"Hakeem Olajuwon C","Unnamed: 5":"Karl Malone F","Unnamed: 6":"Scottie Pippen F","Unnamed: 7":"Latrell Sprewell G","Unnamed: 8":"John Stockton G"}
{"Season":"1993-94","Lg":"NBA","Tm":"2nd","Voting":"(V)","Unnamed: 4":"David Robinson C","Unnamed: 5":"Charles Barkley F","Unnamed: 6":"Shawn Kemp F","Unnamed: 7":"Kevin Johnson G","Unnamed: 8":"Mitch Richmond G"}
{"Season":"1993-94","Lg":"NBA","Tm":"3rd","Voting":"(V)","Unnamed: 4":"Shaquille O'Neal C","Unnamed: 5":"Derrick Coleman F","Unnamed: 6":"Dominique Wilkins F","Unnamed: 7":"Gary Payton G","Unnamed: 8":"Mark Price G"}
{"Season":"1992-93","Lg":"NBA","Tm":"1st","Voting":"(V)","Unnamed: 4":"Hakeem Olajuwon C","Unnamed: 5":"Charles Barkley F","Unnamed: 6":"Karl Malone F","Unnamed: 7":"Michael Jordan G","Unnamed: 8":"Mark Price G"}
{"Season":"1992-93","Lg":"NBA","Tm":"2nd","Voting":"(V)","Unnamed: 4":"Patrick Ewing C","Unnamed: 5":"Larry Johnson F","Unnamed: 6":"Dominique Wilkins F","Unnamed: 7":"Joe Dumars G","Unnamed: 8":"John Stockton G"}
{"Season":"1992-93","Lg":"NBA","Tm":"3rd","Voting":"(V)","Unnamed: 4":"David Robinson C","Unnamed: 5":"Derrick Coleman F","Unnamed: 6":"Scottie Pippen F","Unnamed: 7":"Tim Hardaway G","Unnamed: 8":"Dra\u017een Petrovi\u0107 G"}
{"Season":"1991-92","Lg":"NBA","Tm":"1st","Voting":"(V)","Unnamed: 4":"David Robinson C","Unnamed: 5":"Karl Malone F","Unnamed: 6":"Chris Mullin F","Unnamed: 7":"Clyde Drexler G","Unnamed: 8":"Michael Jordan G"}
{"Season":"1991-92","Lg":"NBA","Tm":"2nd","Voting":"(V)","Unnamed: 4":"Patrick Ewing C","Unnamed: 5":"Charles Barkley F","Unnamed: 6":"Scottie Pippen F","Unnamed: 7":"Tim Hardaway G","Unnamed: 8":"John Stockton G"}
{"Season":"1991-92","Lg":"NBA","Tm":"3rd","Voting":"(V)","Unnamed: 4":"Brad Daugherty C","Unnamed: 5":"Dennis Rodman F","Unnamed: 6":"Kevin Willis F","Unnamed: 7":"Kevin Johnson G","Unnamed: 8":"Mark Price G"}
{"Season":"1990-91","Lg":"NBA","Tm":"1st","Voting":"(V)","Unnamed: 4":"David Robinson C","Unnamed: 5":"Charles Barkley F","Unnamed: 6":"Karl Malone F","Unnamed: 7":"Magic Johnson G","Unnamed: 8":"Michael Jordan G"}
{"Season":"1990-91","Lg":"NBA","Tm":"2nd","Voting":"(V)","Unnamed: 4":"Patrick Ewing C","Unnamed: 5":"Chris Mullin F","Unnamed: 6":"Dominique Wilkins F","Unnamed: 7":"Clyde Drexler G","Unnamed: 8":"Kevin Johnson G"}
{"Season":"1990-91","Lg":"NBA","Tm":"3rd","Voting":"(V)","Unnamed: 4":"Hakeem Olajuwon C","Unnamed: 5":"Bernard King F","Unnamed: 6":"James Worthy F","Unnamed: 7":"Joe Dumars G","Unnamed: 8":"John Stockton G"}
{"Season":"1989-90","Lg":"NBA","Tm":"1st","Voting":"(V)","Unnamed: 4":"Patrick Ewing C","Unnamed: 5":"Charles Barkley F","Unnamed: 6":"Karl Malone F","Unnamed: 7":"Magic Johnson G","Unnamed: 8":"Michael Jordan G"}
{"Season":"1989-90","Lg":"NBA","Tm":"2nd","Voting":"(V)","Unnamed: 4":"Hakeem Olajuwon C","Unnamed: 5":"Larry Bird F","Unnamed: 6":"Tom Chambers F","Unnamed: 7":"Kevin Johnson G","Unnamed: 8":"John Stockton G"}
{"Season":"1989-90","Lg":"NBA","Tm":"3rd","Voting":"(V)","Unnamed: 4":"David Robinson C","Unnamed: 5":"Chris Mullin F","Unnamed: 6":"James Worthy F","Unnamed: 7":"Clyde Drexler G","Unnamed: 8":"Joe Dumars G"}
{"Season":"1988-89","Lg":"NBA","Tm":"1st","Voting":"(V)","Unnamed: 4":"Hakeem Olajuwon C","Unnamed: 5":"Charles Barkley F","Unnamed: 6":"Karl Malone F","Unnamed: 7":"Magic Johnson G","Unnamed: 8":"Michael Jordan G"}
{"Season":"1988-89","Lg":"NBA","Tm":"2nd","Voting":"(V)","Unnamed: 4":"Patrick Ewing C","Unnamed: 5":"Tom Chambers F","Unnamed: 6":"Chris Mullin F","Unnamed: 7":"Kevin Johnson G","Unnamed: 8":"John Stockton G"}
{"Season":"1988-89","Lg":"NBA","Tm":"3rd","Voting":"(V)","Unnamed: 4":"Robert Parish C","Unnamed: 5":"Terry Cummings F","Unnamed: 6":"Dominique Wilkins F","Unnamed: 7":"Dale Ellis G","Unnamed: 8":"Mark Price G"}
{"Season":"1987-88","Lg":"NBA","Tm":"1st","Voting":"(V)","Unnamed: 4":"Hakeem Olajuwon C","Unnamed: 5":"Charles Barkley F","Unnamed: 6":"Larry Bird F","Unnamed: 7":"Magic Johnson G","Unnamed: 8":"Michael Jordan G"}
{"Season":"1987-88","Lg":"NBA","Tm":"2nd","Voting":"(V)","Unnamed: 4":"Patrick Ewing C","Unnamed: 5":"Karl Malone F","Unnamed: 6":"Dominique Wilkins F","Unnamed: 7":"Clyde Drexler G","Unnamed: 8":"John Stockton G"}
{"Season":"1986-87","Lg":"NBA","Tm":"1st","Voting":"(V)","Unnamed: 4":"Hakeem Olajuwon C","Unnamed: 5":"Larry Bird F","Unnamed: 6":"Kevin McHale F","Unnamed: 7":"Magic Johnson G","Unnamed: 8":"Michael Jordan G"}
{"Season":"1986-87","Lg":"NBA","Tm":"2nd","Voting":"(V)","Unnamed: 4":"Moses Malone C","Unnamed: 5":"Charles Barkley F","Unnamed: 6":"Dominique Wilkins F","Unnamed: 7":"Fat Lever G","Unnamed: 8":"Isiah Thomas G"}
{"Season":"1985-86","Lg":"NBA","Tm":"1st","Voting":"(V)","Unnamed: 4":"Kareem Abdul-Jabbar C","Unnamed: 5":"Larry Bird F","Unnamed: 6":"Dominique Wilkins F","Unnamed: 7":"Magic Johnson G","Unnamed: 8":"Isiah Thomas G"}
{"Season":"1985-86","Lg":"NBA","Tm":"2nd","Voting":"(V)","Unnamed: 4":"Hakeem Olajuwon C","Unnamed: 5":"Charles Barkley F","Unnamed: 6":"Alex English F","Unnamed: 7":"Sidney Moncrief G","Unnamed: 8":"Alvin Robertson G"}
{"Season":"1984-85","Lg":"NBA","Tm":"1st","Voting":"(V)","Unnamed: 4":"Moses Malone C","Unnamed: 5":"Larry Bird F","Unnamed: 6":"Bernard King F","Unnamed: 7":"Magic Johnson G","Unnamed: 8":"Isiah Thomas G"}
{"Season":"1984-85","Lg":"NBA","Tm":"2nd","Voting":"(V)","Unnamed: 4":"Kareem Abdul-Jabbar C","Unnamed: 5":"Terry Cummings F","Unnamed: 6":"Ralph Sampson F","Unnamed: 7":"Michael Jordan G","Unnamed: 8":"Sidney Moncrief G"}
{"Season":"1983-84","Lg":"NBA","Tm":"1st","Voting":"(V)","Unnamed: 4":"Kareem Abdul-Jabbar C","Unnamed: 5":"Larry Bird F","Unnamed: 6":"Bernard King F","Unnamed: 7":"Magic Johnson G","Unnamed: 8":"Isiah Thomas G"}
{"Season":"1983-84","Lg":"NBA","Tm":"2nd","Voting":"(V)","Unnamed: 4":"Moses Malone C","Unnamed: 5":"Adrian Dantley F","Unnamed: 6":"Julius Erving F","Unnamed: 7":"Sidney Moncrief G","Unnamed: 8":"Jim Paxson G"}
{"Season":"1982-83","Lg":"NBA","Tm":"1st","Voting":"(V)","Unnamed: 4":"Moses Malone C","Unnamed: 5":"Larry Bird F","Unnamed: 6":"Julius Erving F","Unnamed: 7":"Magic Johnson G","Unnamed: 8":"Sidney Moncrief G"}
{"Season":"1982-83","Lg":"NBA","Tm":"2nd","Voting":"(V)","Unnamed: 4":"Kareem Abdul-Jabbar C","Unnamed: 5":"Alex English F","Unnamed: 6":"Buck Williams F","Unnamed: 7":"George Gervin G","Unnamed: 8":"Isiah Thomas G"}
{"Season":"1981-82","Lg":"NBA","Tm":"1st","Voting":"(V)","Unnamed: 4":"Moses Malone C","Unnamed: 5":"Larry Bird F","Unnamed: 6":"Julius Erving F","Unnamed: 7":"George Gervin G","Unnamed: 8":"Gus Williams G"}
{"Season":"1981-82","Lg":"NBA","Tm":"2nd","Voting":"(V)","Unnamed: 4":"Robert Parish C","Unnamed: 5":"Alex English F","Unnamed: 6":"Bernard King F","Unnamed: 7":"Magic Johnson G","Unnamed: 8":"Sidney Moncrief G"}
{"Season":"1980-81","Lg":"NBA","Tm":"1st","Voting":"(V)","Unnamed: 4":"Kareem Abdul-Jabbar C","Unnamed: 5":"Larry Bird F","Unnamed: 6":"Julius Erving F","Unnamed: 7":"George Gervin G","Unnamed: 8":"Dennis Johnson G"}
{"Season":"1980-81","Lg":"NBA","Tm":"2nd","Voting":"(V)","Unnamed: 4":"Moses Malone C","Unnamed: 5":"Adrian Dantley F","Unnamed: 6":"Marques Johnson F","Unnamed: 7":"Tiny Archibald G","Unnamed: 8":"Otis Birdsong G"}
{"Season":"1979-80","Lg":"NBA","Tm":"1st","Voting":"(V)","Unnamed: 4":"Kareem Abdul-Jabbar C","Unnamed: 5":"Larry Bird F","Unnamed: 6":"Julius Erving F","Unnamed: 7":"George Gervin G","Unnamed: 8":"Paul Westphal G"}
{"Season":"1979-80","Lg":"NBA","Tm":"2nd","Voting":"(V)","Unnamed: 4":"Moses Malone C","Unnamed: 5":"Marques Johnson F","Unnamed: 6":"Dan Roundfield F","Unnamed: 7":"Dennis Johnson G","Unnamed: 8":"Gus Williams G"}
{"Season":"1978-79","Lg":"NBA","Tm":"1st","Voting":"(V)","Unnamed: 4":"Moses Malone C","Unnamed: 5":"Elvin Hayes F","Unnamed: 6":"Marques Johnson F","Unnamed: 7":"George Gervin G","Unnamed: 8":"Paul Westphal G"}
{"Season":"1978-79","Lg":"NBA","Tm":"2nd","Voting":"(V)","Unnamed: 4":"Kareem Abdul-Jabbar C","Unnamed: 5":"Bob Dandridge F","Unnamed: 6":"Walter Davis F","Unnamed: 7":"Phil Ford G","Unnamed: 8":"World B. Free G"}
{"Season":"1977-78","Lg":"NBA","Tm":"1st","Voting":"(V)","Unnamed: 4":"Bill Walton C","Unnamed: 5":"Julius Erving F","Unnamed: 6":"Truck Robinson F","Unnamed: 7":"George Gervin G","Unnamed: 8":"David Thompson G"}
{"Season":"1977-78","Lg":"NBA","Tm":"2nd","Voting":"(V)","Unnamed: 4":"Kareem Abdul-Jabbar C","Unnamed: 5":"Walter Davis F","Unnamed: 6":"Maurice Lucas F","Unnamed: 7":"Pete Maravich G","Unnamed: 8":"Paul Westphal G"}
{"Season":"1976-77","Lg":"NBA","Tm":"1st","Voting":"(V)","Unnamed: 4":"Kareem Abdul-Jabbar C","Unnamed: 5":"Elvin Hayes F","Unnamed: 6":"David Thompson F","Unnamed: 7":"Pete Maravich G","Unnamed: 8":"Paul Westphal G"}
{"Season":"1976-77","Lg":"NBA","Tm":"2nd","Voting":"(V)","Unnamed: 4":"Bill Walton C","Unnamed: 5":"Julius Erving F","Unnamed: 6":"George McGinnis F","Unnamed: 7":"George Gervin G","Unnamed: 8":"Jo Jo White G"}
{"Season":"1975-76","Lg":"NBA","Tm":"1st","Voting":"(V)","Unnamed: 4":"Kareem Abdul-Jabbar C","Unnamed: 5":"Rick Barry F","Unnamed: 6":"George McGinnis F","Unnamed: 7":"Tiny Archibald G","Unnamed: 8":"Pete Maravich G"}
{"Season":"1975-76","Lg":"NBA","Tm":"2nd","Voting":"(V)","Unnamed: 4":"Dave Cowens C","Unnamed: 5":"John Havlicek F","Unnamed: 6":"Elvin Hayes F","Unnamed: 7":"Phil Smith G","Unnamed: 8":"Randy Smith G"}
{"Season":"1974-75","Lg":"NBA","Tm":"1st","Voting":"(V)","Unnamed: 4":"Bob McAdoo C","Unnamed: 5":"Rick Barry F","Unnamed: 6":"Elvin Hayes F","Unnamed: 7":"Tiny Archibald G","Unnamed: 8":"Walt Frazier G"}
{"Season":"1974-75","Lg":"NBA","Tm":"2nd","Voting":"(V)","Unnamed: 4":"Dave Cowens C","Unnamed: 5":"John Havlicek F","Unnamed: 6":"Spencer Haywood F","Unnamed: 7":"Phil Chenier G","Unnamed: 8":"Jo Jo White G"}
{"Season":"1973-74","Lg":"NBA","Tm":"1st","Voting":"(V)","Unnamed: 4":"Kareem Abdul-Jabbar C","Unnamed: 5":"Rick Barry F","Unnamed: 6":"John Havlicek F","Unnamed: 7":"Walt Frazier G","Unnamed: 8":"Gail Goodrich G"}
{"Season":"1973-74","Lg":"NBA","Tm":"2nd","Voting":"(V)","Unnamed: 4":"Bob McAdoo C","Unnamed: 5":"Elvin Hayes F","Unnamed: 6":"Spencer Haywood F","Unnamed: 7":"Dave Bing G","Unnamed: 8":"Norm Van Lier G"}
{"Season":"1972-73","Lg":"NBA","Tm":"1st","Voting":"(V)","Unnamed: 4":"Kareem Abdul-Jabbar C","Unnamed: 5":"John Havlicek F","Unnamed: 6":"Spencer Haywood F","Unnamed: 7":"Tiny Archibald G","Unnamed: 8":"Jerry West G"}
{"Season":"1972-73","Lg":"NBA","Tm":"2nd","Voting":"(V)","Unnamed: 4":"Dave Cowens C","Unnamed: 5":"Rick Barry F","Unnamed: 6":"Elvin Hayes F","Unnamed: 7":"Walt Frazier G","Unnamed: 8":"Pete Maravich G"}
{"Season":"1971-72","Lg":"NBA","Tm":"1st","Voting":"(V)","Unnamed: 4":"Kareem Abdul-Jabbar C","Unnamed: 5":"John Havlicek F","Unnamed: 6":"Spencer Haywood F","Unnamed: 7":"Walt Frazier G","Unnamed: 8":"Jerry West G"}
{"Season":"1971-72","Lg":"NBA","Tm":"2nd","Voting":"(V)","Unnamed: 4":"Wilt Chamberlain C","Unnamed: 5":"Billy Cunningham F","Unnamed: 6":"Bob Love F","Unnamed: 7":"Tiny Archibald G","Unnamed: 8":"Archie Clark G"}
{"Season":"1970-71","Lg":"NBA","Tm":"1st","Voting":"(V)","Unnamed: 4":"Kareem Abdul-Jabbar C","Unnamed: 5":"Billy Cunningham F","Unnamed: 6":"John Havlicek F","Unnamed: 7":"Dave Bing G","Unnamed: 8":"Jerry West G"}
{"Season":"1970-71","Lg":"NBA","Tm":"2nd","Voting":"(V)","Unnamed: 4":"Willis Reed C","Unnamed: 5":"Gus Johnson F","Unnamed: 6":"Bob Love F","Unnamed: 7":"Walt Frazier G","Unnamed: 8":"Oscar Robertson G"}
{"Season":"1969-70","Lg":"NBA","Tm":"1st","Voting":"(V)","Unnamed: 4":"Willis Reed C","Unnamed: 5":"Billy Cunningham F","Unnamed: 6":"Connie Hawkins F","Unnamed: 7":"Walt Frazier G","Unnamed: 8":"Jerry West G"}
{"Season":"1969-70","Lg":"NBA","Tm":"2nd","Voting":"(V)","Unnamed: 4":"Kareem Abdul-Jabbar C","Unnamed: 5":"John Havlicek F","Unnamed: 6":"Gus Johnson F","Unnamed: 7":"Lou Hudson G","Unnamed: 8":"Oscar Robertson G"}
{"Season":"1968-69","Lg":"NBA","Tm":"1st","Voting":"(V)","Unnamed: 4":"Wes Unseld C","Unnamed: 5":"Elgin Baylor F","Unnamed: 6":"Billy Cunningham F","Unnamed: 7":"Earl Monroe G","Unnamed: 8":"Oscar Robertson G"}
{"Season":"1968-69","Lg":"NBA","Tm":"2nd","Voting":"(V)","Unnamed: 4":"Willis Reed C","Unnamed: 5":"Dave DeBusschere F","Unnamed: 6":"John Havlicek F","Unnamed: 7":"Hal Greer G","Unnamed: 8":"Jerry West G"}
{"Season":"1967-68","Lg":"NBA","Tm":"1st","Voting":"(V)","Unnamed: 4":"Wilt Chamberlain C","Unnamed: 5":"Elgin Baylor F","Unnamed: 6":"Jerry Lucas F","Unnamed: 7":"Dave Bing G","Unnamed: 8":"Oscar Robertson G"}
{"Season":"1967-68","Lg":"NBA","Tm":"2nd","Voting":"(V)","Unnamed: 4":"Bill Russell C","Unnamed: 5":"John Havlicek F","Unnamed: 6":"Willis Reed F","Unnamed: 7":"Hal Greer G","Unnamed: 8":"Jerry West G"}
{"Season":"1966-67","Lg":"NBA","Tm":"1st","Voting":"(V)","Unnamed: 4":"Wilt Chamberlain C","Unnamed: 5":"Rick Barry F","Unnamed: 6":"Elgin Baylor F","Unnamed: 7":"Oscar Robertson G","Unnamed: 8":"Jerry West G"}
{"Season":"1966-67","Lg":"NBA","Tm":"2nd","Voting":"(V)","Unnamed: 4":"Bill Russell C","Unnamed: 5":"Jerry Lucas F","Unnamed: 6":"Willis Reed F","Unnamed: 7":"Hal Greer G","Unnamed: 8":"Sam Jones G"}
